{
	"configurations" : 
	[
		{
			"directories" : 
			[
				{
					"build" : ".",
					"jsonFile" : "directory-.-Debug-f5ebdc15457944623624.json",
					"minimumCMakeVersion" : 
					{
						"string" : "3.25"
					},
					"projectIndex" : 0,
					"source" : ".",
					"targetIndexes" : 
					[
						0
					]
				}
			],
			"name" : "Debug",
			"projects" : 
			[
				{
					"directoryIndexes" : 
					[
						0
					],
					"name" : "_094________",
					"targetIndexes" : 
					[
						0
					]
				}
			],
			"targets" : 
			[
				{
					"directoryIndex" : 0,
					"id" : "_094________::@6890427a1f51a3e7e1df",
					"jsonFile" : "target-_094________-Debug-237799a100f1b1c0340c.json",
					"name" : "_094________",
					"projectIndex" : 0
				}
			]
		}
	],
	"kind" : "codemodel",
	"paths" : 
	{
		"build" : "/Users/nozerose/Desktop/2023\ud559\ub144\ub3c4 1\ud559\uae30 \uc218\uc5c5/CB3500572-063 C++\ud504\ub85c\uadf8\ub798\ubc0d\uacfc\uc2e4\uc2b5(Prof.\uae40\ud0dc\uc5f0)/\uc2e4\uc2b5/\uc2e4\uc2b5 094 - \ud504\ub85c\uadf8\ub7a8 \uc2e4\ud589 \uc911 \ub3d9\uc791 \ubcc0\ud654 \uc2dc\ud0a4\uae30/cmake-build-debug",
		"source" : "/Users/nozerose/Desktop/2023\ud559\ub144\ub3c4 1\ud559\uae30 \uc218\uc5c5/CB3500572-063 C++\ud504\ub85c\uadf8\ub798\ubc0d\uacfc\uc2e4\uc2b5(Prof.\uae40\ud0dc\uc5f0)/\uc2e4\uc2b5/\uc2e4\uc2b5 094 - \ud504\ub85c\uadf8\ub7a8 \uc2e4\ud589 \uc911 \ub3d9\uc791 \ubcc0\ud654 \uc2dc\ud0a4\uae30"
	},
	"version" : 
	{
		"major" : 2,
		"minor" : 4
	}
}
